proselint/__init__.py
proselint/__main__.py
proselint/backports.py
proselint/checks/__init__.py
proselint/checks/annotations.py
proselint/checks/archaism.py
proselint/checks/cliches/__init__.py
proselint/checks/cliches/diction
proselint/checks/cliches/garner
proselint/checks/cliches/hell.py
proselint/checks/cliches/misc.py
proselint/checks/cliches/write-good
proselint/checks/dates_times/__init__.py
proselint/checks/dates_times/am_pm.py
proselint/checks/dates_times/dates.py
proselint/checks/hedging.py
proselint/checks/industrial_language/__init__.py
proselint/checks/industrial_language/airlinese.py
proselint/checks/industrial_language/bureaucratese.py
proselint/checks/industrial_language/chatspeak.py
proselint/checks/industrial_language/commercialese.py
proselint/checks/industrial_language/corporate_speak.py
proselint/checks/industrial_language/jargon.py
proselint/checks/lexical_illusions.py
proselint/checks/malapropisms.py
proselint/checks/misc/__init__.py
proselint/checks/misc/apologizing.py
proselint/checks/misc/back_formations.py
proselint/checks/misc/but.py
proselint/checks/misc/capitalization.py
proselint/checks/misc/composition.py
proselint/checks/misc/currency.py
proselint/checks/misc/debased.py
proselint/checks/misc/false_plurals.py
proselint/checks/misc/greylist.py
proselint/checks/misc/illogic.py
proselint/checks/misc/inferior_superior.py
proselint/checks/misc/institution_name.py
proselint/checks/misc/latin.py
proselint/checks/misc/many_a.py
proselint/checks/misc/metadiscourse.py
proselint/checks/misc/narcissism.py
proselint/checks/misc/not_guilty.py
proselint/checks/misc/phrasal_adjectives.py
proselint/checks/misc/preferred_forms.py
proselint/checks/misc/pretension.py
proselint/checks/misc/professions.py
proselint/checks/misc/scare_quotes.py
proselint/checks/misc/suddenly.py
proselint/checks/misc/tense_present.py
proselint/checks/misc/waxed.py
proselint/checks/misc/whence.py
proselint/checks/mixed_metaphors.py
proselint/checks/mondegreens.py
proselint-0.16.0.dist-info/WHEEL
proselint-0.16.0.dist-info/entry_points.txt
proselint-0.16.0.dist-info/METADATA
proselint-0.16.0.dist-info/RECORD
