Metadata-Version: 2.3
Name: proselint
Version: 0.16.0
Summary: A linter for prose.
Author: Amperser Labs
Author-email: Amperser Labs <hello@amperser.com>
License: Copyright © 2014–2015, Jordan Suchow, Michael Pacer, and Lara A. Ross 
Classifier: Programming Language :: Python :: Implementation :: CPython
Classifier: Programming Language :: Python :: 3
Classifier: Programming Language :: Python :: 3.10
Classifier: Programming Language :: Python :: 3.11
Classifier: Programming Language :: Python :: 3.12
Classifier: Programming Language :: Python :: 3.13
Classifier: Programming Language :: Python :: 3.14
Classifier: License :: OSI Approved :: BSD License
Requires-Dist: google-re2>=1.1.20251105
Requires-Dist: google-re2-stubs>=0.1.1
Requires-Python: >=3.10
Project-URL: Homepage, https://github.com/amperser/proselint
Project-URL: Issues, https://github.com/amperser/proselint/issues
Project-URL: Repository, https://github.com/amperser/proselint
